yafowil.widget.image-1.7-py3.9-nspkg.pth
yafowil/widget/image/__init__.py
yafowil/widget/image/configure.zcml
yafowil/widget/image/example.py
yafowil/widget/image/tests.py
yafowil/widget/image/utils.py
yafowil/widget/image/widget.py
yafowil/widget/image/locales/yafowil.widget.image.pot
yafowil/widget/image/locales/de/LC_MESSAGES/yafowil.widget.image.mo
yafowil/widget/image/locales/de/LC_MESSAGES/yafowil.widget.image.po
yafowil/widget/image/locales/en/LC_MESSAGES/yafowil.widget.image.mo
yafowil/widget/image/locales/en/LC_MESSAGES/yafowil.widget.image.po
yafowil/widget/image/resources/widget.css
yafowil/widget/image/resources/widget.js
yafowil/widget/image/testing/__init__.py
yafowil/widget/image/testing/dummy.jpg
yafowil/widget/image/testing/dummy.pdf
yafowil/widget/image/testing/dummy.png
yafowil_widget_image-1.7.dist-info/licenses/LICENSE.rst
yafowil_widget_image-1.7.dist-info/METADATA
yafowil_widget_image-1.7.dist-info/WHEEL
yafowil_widget_image-1.7.dist-info/entry_points.txt
yafowil_widget_image-1.7.dist-info/namespace_packages.txt
yafowil_widget_image-1.7.dist-info/top_level.txt
yafowil_widget_image-1.7.dist-info/RECORD
